{"cameraMode":{"drawMode":0,"name":"Shaded","section":"Shading Mode"},"sceneLighting":true,"audioPlay":false,"sceneViewState":{"m_AlwaysRefresh":false,"showFog":false,"showSkybox":false,"showFlares":false,"showImageEffects":false,"showParticleSystems":false,"showVisualEffectGraphs":true,"m_FxEnabled":true},"in2DMode":false,"pivot":{"x":-52.32575225830078,"y":-39.453521728515628,"z":0.247955322265625},"rotation":{"x":0.3726147711277008,"y":-0.4122064411640167,"z":0.18974199891090394,"w":0.8094742894172669},"size":108.54121398925781,"orthographic":false}